apiverve_routingnumberlookup/__init__.py
apiverve_routingnumberlookup/apiClient.py
apiverve_routingnumberlookup/exceptions.py
apiverve_routingnumberlookup/setup.py
apiverve_routingnumberlookup/setup_dep.py
apiverve_routingnumberlookup/tests/__init__.py
apiverve_routingnumberlookup/tests/test_api.py
apiverve_routingnumberlookup-1.1.5.dist-info/LICENSE
apiverve_routingnumberlookup-1.1.5.dist-info/METADATA
apiverve_routingnumberlookup-1.1.5.dist-info/WHEEL
apiverve_routingnumberlookup-1.1.5.dist-info/top_level.txt
apiverve_routingnumberlookup-1.1.5.dist-info/RECORD
